[{"productImage":"http://via.placeholder.com/180?text=HiSpeed-Tonic","brandName":"Acme","productName":"Hi-Speed Tonic","packageDetail":"500ml","price":1000},{"productImage":"http://via.placeholder.com/180?text=Iron+Pellets","brandName":"AcmeX","productName":"Iron Pellets","packageDetail":"10 units","price":1500},{"productImage":"http://via.placeholder.com/180?text=Invisible+Paint","brandName":"AcmeIN","productName":"Invisible Paint","packageDetail":"1000ml","price":2000},{"productImage":"http://via.placeholder.com/180?text=Snow+Machine","brandName":"Acme","productName":"Snow Machine","packageDetail":"1 unit","price":5000},{"productImage":"http://via.placeholder.com/180?text=Badger+Trap","brandName":"AcmeX","productName":"Badger Trap","packageDetail":"1 unit","price":500},{"productImage":"http://via.placeholder.com/180?text=Spring+Boots","brandName":"AcmeUK","productName":"Spring Boots","packageDetail":"1 pair","price":3500}]